mvar/__init__.py
mvar/mvar.py
mvar-1.0.0.dist-info/LICENSE
mvar-1.0.0.dist-info/METADATA
mvar-1.0.0.dist-info/WHEEL
mvar-1.0.0.dist-info/top_level.txt
mvar-1.0.0.dist-info/RECORD
