Metadata-Version: 2.1
Name: mvar
Version: 1.0.0
Summary: Python implementation of Haskell's Control.Concurrent.MVar
Home-page: https://github.com/gabrik/mvar-python
Author: Gabriele Baldoni, Artem Chirkin
Author-email: UNKNOWN
License: Apache 2.O
Platform: UNKNOWN
Classifier: Development Status :: 5 - Production/Stable
Classifier: Intended Audience :: Developers
Classifier: License :: OSI Approved :: Apache Software License
Classifier: Operating System :: OS Independent
Classifier: Programming Language :: Python :: 3 :: Only
